SimpleImageTransport/__init__.py
SimpleImageTransport/local.py
SimpleImageTransport/remote.py
SimpleImageTransport-1.3.dist-info/LICENSE
SimpleImageTransport-1.3.dist-info/METADATA
SimpleImageTransport-1.3.dist-info/WHEEL
SimpleImageTransport-1.3.dist-info/top_level.txt
SimpleImageTransport-1.3.dist-info/RECORD
