Metadata-Version: 2.1
Name: SimpleImageTransport
Version: 1.3
Summary: Simple python 2/3 library for transporting images to a remote machine, applying transformations and returning a response.
Home-page: https://github.com/RaymondKirk/SimpleImageTransport
Author: Raymond Tunstill
Author-email: ray.tunstill@live.co.uk
License: UNKNOWN
Platform: UNKNOWN
Classifier: License :: OSI Approved :: MIT License
Classifier: Programming Language :: Python :: 2
Classifier: Programming Language :: Python :: 2.7
Classifier: Programming Language :: Python :: 3
Classifier: Programming Language :: Python :: 3.7
Requires-Dist: opencv-python
Requires-Dist: Flask
Requires-Dist: numpy
Requires-Dist: requests
Requires-Dist: jsonpickle
